[
  { "map": "greenisland", "x": 1450.3433, "y": 360.0002 },
  { "map": "greenisland", "x": 1121.17166, "y": 385.98 },
  { "map": "greenisland", "x": 1295.49383, "y": 404.0066 },
  { "map": "greenisland", "x": 1455.4396, "y": 440.232 },
  { "map": "greenisland", "x": 1179.05, "y": 441.14 },
  { "map": "greenisland", "x": 1387.39094, "y": 464.9845 },
  { "map": "greenisland", "x": 1388.66582, "y": 469.6592 },
  { "map": "greenisland", "x": 1387.90375, "y": 474.9792 },
  { "map": "greenisland", "x": 1451.2661, "y": 481.1291 },
  { "map": "greenisland", "x": 1308.14914, "y": 481.7407 },
  { "map": "greenisland", "x": 1199.81598, "y": 490.1066 },
  { "map": "greenisland", "x": 1181.09867, "y": 513.4305 },
  { "map": "greenisland", "x": 1460.87934, "y": 518.85016 },
  { "map": "greenisland", "x": 1300.5897, "y": 527.4809 },
  { "map": "greenisland", "x": 1322.8716, "y": 542.1223 },
  { "map": "greenisland", "x": 1353.8459, "y": 568.87594 },
  { "map": "greenisland", "x": 1419.43652, "y": 571.23965 },
  { "map": "greenisland", "x": 1530.1688, "y": 582.5502 },
  { "map": "greenisland", "x": 1443.8849, "y": 611.75008 },
  { "map": "greenisland", "x": 1217.4961, "y": 655.18574 },
  { "map": "greenisland", "x": 1617.8998, "y": 706.5135 },
  { "map": "greenisland", "x": 1520.5579, "y": 718.48633 },
  { "map": "greenisland", "x": 1414.25934, "y": 740.5419 },
  { "map": "greenisland", "x": 1324.07586, "y": 811.57418 },
  { "map": "greenisland", "x": 1481.6308, "y": 834.5533 },
  { "map": "greenisland", "x": 1436.99965, "y": 887.50762 },
  { "map": "greenisland", "x": 1505.8825, "y": 896.6872 },
  { "map": "greenisland", "x": 354.94664, "y": 1274.13824 },
  { "map": "greenisland", "x": 407.18664, "y": 1301.51824 },
  { "map": "greenisland", "x": 503.41332, "y": 1309.22388 },
  { "map": "greenisland", "x": 1310.68598, "y": 1789.41555 },
  { "map": "greenisland", "x": 1384.10258, "y": 1796.828 },
  { "map": "greenisland", "x": 1306.97203, "y": 1817.6432 }
]
